{"Book Value (BVPS)": "33.22", "Shareholders": {"Shareholder Stake": ["27.6667%", "6.3699%", "6.00%", "0.0276%", "0.0044%", "0.0044%", "0.0022%"], "Shareholder Name": ["Al Othaim Holding Co", "General Organization for Social Insurance - Saudi Arabia", "Abdullah Saleh Ali Al Othaim", "Bahauddin Barakat Al Sherbeni", "Abdulsalam Saleh Abdul Aziz Alrajhi", "Fahad Abdullah Saleh Ali Al Othaim", "Abdulaziz Abdullah Saleh Al Othaim"]}, "Description": "Abdullah Al Othaim Markets (known as: A.Othaim Market) is a public company, listed on Saudi Stock Exchange \u201cTadawul\u201d (TDWL) since July 2008. A.Othaim Market operates within the Food and Staples Retailing sector focusing on Hypermarkets and Super Centers. It has Companies operating across Bosnia and Herzegovina, Saudi Arabia, Turkey and Egypt. A.Othaim Market is based in Riyadh, Saudi Arabia and was established in May 1980.", "Close Price": "173.60", "Market Cap": "7,812,000,000.00", "P/B Ratio": "5.08", "EPS": "14.89", "P/E Ratio": "16.88", "Price Change %": "2.82%", "Market Stats": {"High": "170.00", "Volume": "102,409", "Low": "167.20", "Previous Close": "168.58", "Open": "169.80", "Turnover": "17,249,830.00"}, "Par Value": "10.00", "Company Name": "Abdullah Al Othaim Markets Co (4001)", "Management Team": {"Name": ["Abdullah Saleh Ali Al Othaim", "Abdulaziz Saleh Abdullah Al Rebdi", "Fahad Abdullah Saleh Ali Al Othaim", "Abdulsalam Saleh Abdul Aziz Alrajhi", "Abdulaziz Abdullah Saleh Al Othaim", "Saleh Mohammed Saleh Al Othaim", "Bandr Nasser Hamad Al Tamimi"], "Title": ["Chairman", "Board Members", "Board Members", "Board Members", "Board Members", "Board Members", "Board Members"]}}