{"Book Value (BVPS)": "15.28", "Shareholders": {"Shareholder Stake": ["52.50%", "14.70%", "2.80%"], "Shareholder Name": ["Saudi Arabian Airlines Corp", "National Aviation Ground Support Co Ltd", "Attar Ground Services Ltd"]}, "Description": "Saudi Ground Services Co (known as: SGS) is a public company, listed on Saudi Stock Exchange \u201cTadawul\u201d (TDWL) since June 2015. SGS operates within the Transportation sector focusing on Airport Services. It has Companies operating across Saudi Arabia, working on Diversified Support Services and Airport Services. SGS is based in Jeddah, Saudi Arabia and was established in July 2008.", "Close Price": "37.70", "Market Cap": "7,087,600,000.00", "P/B Ratio": "2.47", "EPS": "1.36", "P/E Ratio": "14.14", "Price Change %": "0.19%", "Market Stats": {"High": "38.20", "Volume": "667,451", "Low": "37.55", "Previous Close": "38.02", "Open": "38.10", "Turnover": "25,274,708.85"}, "Par Value": "10.00", "Company Name": "Saudi Ground Services Co (4031)", "Management Team": {"Name": ["Abdullah Ibrahim Al Hawesh", "Omar Bin Mohamed Siraj Najjar", "Omar Abdullah Jafri", "Ayed Thawab Al Jeaid", "Attian Attia Al Hazmi", "Mansour Abdulaziz Rashid Al Bosaily", "Abdulhadi Ali Saif Shayif", "Mohamed bin Taiwila Alsulami", "Mohammed Abdulaziz Abdulrahman Al Shaya"], "Title": ["Chairman", "CEO", "Board Members", "Board Members", "Board Members", "Board Members", "Board Members", "Board Members", "Board Members"]}}