{"Company Name": "Alinma Tokio Marine Co (8312)", "Description": "Alinma Tokio Marine Co (known as: Alinma Tokio M) is a public company, listed on Saudi Stock Exchange \u201cTadawul\u201d (TDWL) since June 2012. Alinma Tokio M operates within the Insurance sector focusing on Multi-line Insurance. It has company operates across Saudi Arabia. Alinma Tokio M is based in Riyadh, Saudi Arabia and was established in June 2012.", "Market Stats": {"Open": "24.66", "Previous Close": "24.81", "High": "24.82", "Low": "24.48", "Volume": "130,903", "Turnover": "3,237,865.30"}, "Shareholders": {"Shareholder Name": ["Tokyo Marine and Nacedo Fire Insurance Ltd", "Al Inma Bank", "Ali Suliman Ayed Alayed", "Geant Saudi Arabia Ltd", "Essam bin Abdulaziz Banaga", "Khalid Abdullah Al Rumaih"], "Shareholder Stake": ["28.75%", "28.75%", "0.3333%", "0.2222%", "0.0028%", "0.0003%"]}, "Management Team": {"Name": ["Abdulmohsen Bin Abdel Aziz Al Fares", "Jun Hemmi", "Mutlaq Hamad Mutlaq Al Morished", "Haironarai Aiwakowama", "Faisal Ibrahim Ben Suwailem", "Faisal Bin Ibrahim Bin Abdullah Al Suwail", "Hisato Hamada", "Fahad Mohammed Al Semari", "Essam bin Abdulaziz Banaga", "Khalid Abdullah Al Rumaih", "Ali Suliman Ayed Alayed"], "Title": ["Chairman", "CEO", "Board Members", "Board Members", "Board Members", "Board Members", "Board Members", "Board Members", "Board Members", "Board Members", "Board Members"]}, "Close Price": "24.80", "Price Change %": "-0.08%", "Par Value": "10.00", "Market Cap": "744,000,000.00", "Book Value (BVPS)": "9.43", "P/B Ratio": "2.63", "EPS": "0.77", "P/E Ratio": "-224.26"}